transportations_library-0.1.7.dist-info/METADATA
transportations_library-0.1.7.dist-info/WHEEL
transportations_library/__init__.py
transportations_library/transportations_library.cp310-win_amd64.pyd
transportations_library-0.1.7.dist-info/RECORD
