Metadata-Version: 2.4
Name: transportations_library
Version: 0.1.7
Classifier: Programming Language :: Rust
Classifier: Programming Language :: Python :: Implementation :: CPython
Classifier: Programming Language :: Python :: Implementation :: PyPy
Requires-Dist: maturin>=1.9.6
Requires-Dist: cffi
Requires-Dist: pytest>=6.0 ; extra == 'test'
Requires-Dist: pytest-cov ; extra == 'test'
Provides-Extra: test
Author: raynbowy23
Requires-Python: >=3.8
Project-URL: Homepage, https://github.com/crosstraffic/transportations_library
